quatica/__init__.py
quatica/data_gen.py
quatica/decomp/LU.py
quatica/decomp/README.md
quatica/decomp/__init__.py
quatica/decomp/eigen.py
quatica/decomp/hessenberg.py
quatica/decomp/qsvd.py
quatica/decomp/schur.py
quatica/decomp/tridiagonalize.py
quatica/qslst.py
quatica/solver.py
quatica/tensor.py
quatica/utils.py
quatica/visualization.py
quatica-0.1.13.dist-info/WHEEL
quatica-0.1.13.dist-info/METADATA
quatica-0.1.13.dist-info/RECORD
