Metadata-Version: 2.3
Name: quatica
Version: 0.1.13
Summary: Numerical linear algebra for quaternions — fast, practical, and well‑tested
Keywords: quaternion,linear-algebra,matrix,decomposition,svd,pseudoinverse,gmres
Author: Valentin Leplat, Dmitry Beresnev
Author-email: Valentin Leplat <valentin.leplat@gmail.com>, Dmitry Beresnev <dmitry.beresnev@gmail.com>
License: CC0-1.0
Classifier: Development Status :: 4 - Beta
Classifier: Intended Audience :: Science/Research
Classifier: Intended Audience :: Developers
Classifier: License :: CC0 1.0 Universal (CC0 1.0) Public Domain Dedication
Classifier: Programming Language :: Python :: 3
Classifier: Programming Language :: Python :: 3.11
Classifier: Programming Language :: Python :: 3.12
Classifier: Topic :: Scientific/Engineering :: Mathematics
Classifier: Topic :: Software Development :: Libraries :: Python Modules
Requires-Dist: matplotlib>=3.10.3
Requires-Dist: numpy>=2.3.2
Requires-Dist: numpy-quaternion>=2024.0.10
Requires-Dist: scikit-learn>=1.5.0
Requires-Dist: scipy>=1.16.1
Requires-Dist: seaborn>=0.13.0
Requires-Python: >=3.11
Project-URL: Bug Tracker, https://github.com/vleplat/QuatIca/issues
Project-URL: Colab Demo, https://colab.research.google.com/drive/1LQMnpGdSiWZsXjZQrMp1BmVT9Uzt_CKM?usp=sharing
Project-URL: DOI, https://doi.org/10.5281/zenodo.16910158
Project-URL: Documentation, https://vleplat.github.io/QuatIca/
Project-URL: Homepage, https://github.com/vleplat/QuatIca
Project-URL: Repository, https://github.com/vleplat/QuatIca
